jyelib/__init__.py
jyelib/array.py
jyelib/httpcli.py
jyelib-0.1.0.dist-info/licenses/LICENSE
jyelib-0.1.0.dist-info/METADATA
jyelib-0.1.0.dist-info/WHEEL
jyelib-0.1.0.dist-info/top_level.txt
jyelib-0.1.0.dist-info/RECORD
