Metadata-Version: 2.4
Name: jyelib
Version: 0.1.0
Summary: jye lib
Home-page: https://github.com/jye/jyelib
Author: jye
Author-email: jye@example.com
Classifier: Programming Language :: Python :: 3
Classifier: Operating System :: OS Independent
Requires-Python: >=3.6
License-File: LICENSE
Requires-Dist: requests>=2.25.1
Provides-Extra: test
Requires-Dist: pytest>=6.0; extra == "test"
Dynamic: license-file
